KaiyuanRuanjianZhinan/README.md
KaiyuanRuanjianZhinan/__init__.py
KaiyuanRuanjianZhinan/__main__.py
KaiyuanRuanjianZhinan/file.epub
KaiyuanRuanjianZhinan/index.html
KaiyuanRuanjianZhinan/css/__init__.py
KaiyuanRuanjianZhinan/css/annotations.css
KaiyuanRuanjianZhinan/css/main.css
KaiyuanRuanjianZhinan/css/normalize.css
KaiyuanRuanjianZhinan/css/popup.css
KaiyuanRuanjianZhinan/font/__init__.py
KaiyuanRuanjianZhinan/font/fontello.eot
KaiyuanRuanjianZhinan/font/fontello.svg
KaiyuanRuanjianZhinan/font/fontello.ttf
KaiyuanRuanjianZhinan/font/fontello.woff
KaiyuanRuanjianZhinan/img/__init__.py
KaiyuanRuanjianZhinan/img/annotator-glyph-sprite.png
KaiyuanRuanjianZhinan/img/annotator-icon-sprite.png
KaiyuanRuanjianZhinan/img/apple-touch-icon.png
KaiyuanRuanjianZhinan/img/cancelfullscreen.png
KaiyuanRuanjianZhinan/img/close.png
KaiyuanRuanjianZhinan/img/fullscreen.png
KaiyuanRuanjianZhinan/img/loader.gif
KaiyuanRuanjianZhinan/img/menu-icon.png
KaiyuanRuanjianZhinan/img/save.png
KaiyuanRuanjianZhinan/img/saved.png
KaiyuanRuanjianZhinan/img/settings-s.png
KaiyuanRuanjianZhinan/img/settings.png
KaiyuanRuanjianZhinan/img/star.png
KaiyuanRuanjianZhinan/js/__init__.py
KaiyuanRuanjianZhinan/js/epub.js
KaiyuanRuanjianZhinan/js/epub.min.js
KaiyuanRuanjianZhinan/js/epub.min.map
KaiyuanRuanjianZhinan/js/hooks.min.js
KaiyuanRuanjianZhinan/js/hooks.min.map
KaiyuanRuanjianZhinan/js/reader.js
KaiyuanRuanjianZhinan/js/reader.js.map
KaiyuanRuanjianZhinan/js/reader.min.js
KaiyuanRuanjianZhinan/js/reader.min.map
KaiyuanRuanjianZhinan/js/hooks/__init__.py
KaiyuanRuanjianZhinan/js/hooks/extensions/__init__.py
KaiyuanRuanjianZhinan/js/hooks/extensions/highlight.js
KaiyuanRuanjianZhinan/js/libs/__init__.py
KaiyuanRuanjianZhinan/js/libs/jquery.min.js
KaiyuanRuanjianZhinan/js/libs/localforage.min.js
KaiyuanRuanjianZhinan/js/libs/screenfull.js
KaiyuanRuanjianZhinan/js/libs/screenfull.min.js
KaiyuanRuanjianZhinan/js/libs/zip.min.js
KaiyuanRuanjianZhinan/js/plugins/__init__.py
kaiyuan_ruanjian_zhinan-2024.3.5.0.dist-info/METADATA
kaiyuan_ruanjian_zhinan-2024.3.5.0.dist-info/WHEEL
kaiyuan_ruanjian_zhinan-2024.3.5.0.dist-info/entry_points.txt
kaiyuan_ruanjian_zhinan-2024.3.5.0.dist-info/top_level.txt
kaiyuan_ruanjian_zhinan-2024.3.5.0.dist-info/RECORD
